[ {
  "id" : 6,
  "dateOfTravel" : "02/01/2024",
  "travelFor" : "outing",
  "project" : "dotnet",
  "businessUnit" : "csharp-pro",
  "organisation" : "prolifics",
  "trip" : "pune outing",
  "tripDescription" : "pune outing",
  "location" : "domestic",
  "foreignExchange" : "usd",
  "applyFor" : "weekend",
  "other" : "none",
  "travelId" : 5598,
  "approvalStatus" : "approved"
}, {
  "id" : 5,
  "dateOfTravel" : "02/02/2024",
  "travelFor" : "outing",
  "project" : "dotnet",
  "businessUnit" : "csharp-pro",
  "organisation" : "prolifics",
  "trip" : "pune outing",
  "tripDescription" : "pune outing",
  "location" : "domestic",
  "foreignExchange" : "usd",
  "applyFor" : "weekend",
  "other" : "none",
  "travelId" : 5596,
  "approvalStatus" : "approved"
}, {
  "id" : 6,
  "dateOfTravel" : "03/03/2024",
  "travelFor" : "outing",
  "project" : "dotnet",
  "businessUnit" : "csharp-pro",
  "organisation" : "prolifics",
  "trip" : "pune outing",
  "tripDescription" : "pune outing",
  "location" : "domestic",
  "foreignExchange" : "usd",
  "applyFor" : "weekend",
  "other" : "none",
  "travelId" : 5590,
  "approvalStatus" : null
}, {
  "id" : 7,
  "dateOfTravel" : "17/04/2024",
  "travelFor" : "business",
  "project" : "",
  "businessUnit" : "client",
  "organisation" : "",
  "trip" : "up",
  "tripDescription" : "up trip",
  "location" : "domestic",
  "foreignExchange" : "",
  "applyFor" : "self",
  "other" : "",
  "travelId" : 6666,
  "approvalStatus" : null
}, {
  "id" : null,
  "dateOfTravel" : "08/03/2024",
  "travelFor" : "business",
  "project" : "",
  "businessUnit" : "client",
  "organisation" : "",
  "trip" : "mathura",
  "tripDescription" : "holiday",
  "location" : "domestic",
  "foreignExchange" : "",
  "applyFor" : "self",
  "other" : "",
  "travelId" : 7777,
  "approvalStatus" : null
}, {
  "id" : null,
  "dateOfTravel" : "18/03/2024",
  "travelFor" : "business",
  "project" : "",
  "businessUnit" : "client",
  "organisation" : "",
  "trip" : "Jaipur",
  "tripDescription" : "Discussion",
  "location" : "domestic",
  "foreignExchange" : "",
  "applyFor" : "self",
  "other" : "",
  "travelId" : 5555,
  "approvalStatus" : "approved"
}, {
  "id" : null,
  "dateOfTravel" : "16/04/2024",
  "travelFor" : "business",
  "project" : "",
  "businessUnit" : "client",
  "organisation" : "",
  "trip" : "up",
  "tripDescription" : "annual meeting",
  "location" : "domestic",
  "foreignExchange" : "",
  "applyFor" : "self",
  "other" : "",
  "travelId" : 1001,
  "approvalStatus" : null
}, {
  "id" : 11,
  "dateOfTravel" : "02/03/2024",
  "travelFor" : "hvjhgui celebration",
  "project" : "dotfsvbnet",
  "businessUnit" : "ado .net-pro",
  "organisation" : "prolifics",
  "trip" : "mumbai outing",
  "tripDescription" : "mumbai outing",
  "location" : "pune",
  "foreignExchange" : "usd",
  "applyFor" : "dcyjf",
  "other" : "none",
  "travelId" : 8888,
  "approvalStatus" : null
}, {
  "id" : 12,
  "dateOfTravel" : "04/03/2024",
  "travelFor" : "hvjhgui celebration",
  "project" : "dotfsvbnet",
  "businessUnit" : "ado .net-pro",
  "organisation" : "prolifics",
  "trip" : "nagpur outing",
  "tripDescription" : "nagpur outing",
  "location" : "pune",
  "foreignExchange" : "usd",
  "applyFor" : "dcyjf",
  "other" : "none",
  "travelId" : 1101,
  "approvalStatus" : "approved"
}, {
  "id" : 13,
  "dateOfTravel" : "04/03/2024",
  "travelFor" : "hvjhgui celebration",
  "project" : "dotfsvbnet",
  "businessUnit" : "ado .net-pro",
  "organisation" : "prolifics",
  "trip" : "nagpur outing",
  "tripDescription" : "nagpur outing",
  "location" : "pune",
  "foreignExchange" : "usd",
  "applyFor" : "dcyjf",
  "other" : "none",
  "travelId" : 1111,
  "approvalStatus" : "approved"
}, {
  "id" : null,
  "dateOfTravel" : "25/04/2024",
  "travelFor" : "project",
  "project" : "",
  "businessUnit" : "",
  "organisation" : "",
  "trip" : "mp",
  "tripDescription" : "mp trip",
  "location" : "domestic",
  "foreignExchange" : "",
  "applyFor" : "self",
  "other" : "",
  "travelId" : 789,
  "approvalStatus" : null
}, {
  "id" : null,
  "dateOfTravel" : "03/05/2024",
  "travelFor" : "organisation",
  "project" : "",
  "businessUnit" : "",
  "organisation" : "organisation",
  "trip" : "mp",
  "tripDescription" : "mp trip",
  "location" : "domestic",
  "foreignExchange" : "",
  "applyFor" : "self",
  "other" : "",
  "travelId" : 658968,
  "approvalStatus" : null
}, {
  "id" : null,
  "dateOfTravel" : "2024-04-19",
  "travelFor" : "business",
  "project" : "",
  "businessUnit" : "client",
  "organisation" : "",
  "trip" : "HImachal pradesh",
  "tripDescription" : "Holiday",
  "location" : "domestic",
  "foreignExchange" : "",
  "applyFor" : "self",
  "other" : "",
  "travelId" : 1122,
  "approvalStatus" : null
}, {
  "id" : null,
  "dateOfTravel" : "2024-04-20",
  "travelFor" : "business",
  "project" : "",
  "businessUnit" : "client",
  "organisation" : "",
  "trip" : "HImachal pradesh",
  "tripDescription" : "Holiday",
  "location" : "domestic",
  "foreignExchange" : "",
  "applyFor" : "self",
  "other" : "",
  "travelId" : 1123,
  "approvalStatus" : null
}, {
  "id" : null,
  "dateOfTravel" : "2024-04-21",
  "travelFor" : "business",
  "project" : "",
  "businessUnit" : "client",
  "organisation" : "",
  "trip" : "HImachal pradesh",
  "tripDescription" : "Holiday",
  "location" : "domestic",
  "foreignExchange" : "",
  "applyFor" : "self",
  "other" : "",
  "travelId" : 1124,
  "approvalStatus" : null
}, {
  "id" : null,
  "dateOfTravel" : "2024-04-22",
  "travelFor" : "business",
  "project" : "",
  "businessUnit" : "client",
  "organisation" : "",
  "trip" : "HImachal pradesh",
  "tripDescription" : "Holiday",
  "location" : "domestic",
  "foreignExchange" : "",
  "applyFor" : "self",
  "other" : "",
  "travelId" : 1125,
  "approvalStatus" : null
}, {
  "id" : null,
  "dateOfTravel" : "2024-04-23",
  "travelFor" : "business",
  "project" : "",
  "businessUnit" : "client",
  "organisation" : "",
  "trip" : "HImachal pradesh",
  "tripDescription" : "Holiday",
  "location" : "domestic",
  "foreignExchange" : "",
  "applyFor" : "self",
  "other" : "",
  "travelId" : 1126,
  "approvalStatus" : null
}, {
  "id" : null,
  "dateOfTravel" : "2024-04-23",
  "travelFor" : "business",
  "project" : "",
  "businessUnit" : "client",
  "organisation" : "",
  "trip" : "HImachal pradesh",
  "tripDescription" : "Holiday",
  "location" : "domestic",
  "foreignExchange" : "",
  "applyFor" : "self",
  "other" : "",
  "travelId" : 1127,
  "approvalStatus" : null
}, {
  "id" : null,
  "dateOfTravel" : "2024-04-20",
  "travelFor" : "organisation",
  "project" : "",
  "businessUnit" : "",
  "organisation" : "organisation",
  "trip" : "oo",
  "tripDescription" : "oo",
  "location" : "domestic",
  "foreignExchange" : "",
  "applyFor" : "self",
  "other" : "",
  "travelId" : 9090,
  "approvalStatus" : null
}, {
  "id" : null,
  "dateOfTravel" : "2024-04-26",
  "travelFor" : "organisation",
  "project" : "",
  "businessUnit" : "",
  "organisation" : "organisation",
  "trip" : "hdt",
  "tripDescription" : "jhgfjh",
  "location" : "domestic",
  "foreignExchange" : "",
  "applyFor" : "self",
  "other" : "",
  "travelId" : 4567,
  "approvalStatus" : null
}, {
  "id" : null,
  "dateOfTravel" : "2024-04-22",
  "travelFor" : "business",
  "project" : "",
  "businessUnit" : "client",
  "organisation" : "",
  "trip" : "lucknow",
  "tripDescription" : "lucknow trip trip trip",
  "location" : "domestic",
  "foreignExchange" : "",
  "applyFor" : "self",
  "other" : "",
  "travelId" : 4536,
  "approvalStatus" : null
}, {
  "id" : null,
  "dateOfTravel" : "2024-04-26",
  "travelFor" : "business",
  "project" : "",
  "businessUnit" : "client",
  "organisation" : "",
  "trip" : "bd",
  "tripDescription" : "dbt",
  "location" : "domestic",
  "foreignExchange" : "",
  "applyFor" : "self",
  "other" : "",
  "travelId" : 8769,
  "approvalStatus" : null
}, {
  "id" : null,
  "dateOfTravel" : "2024-05-04",
  "travelFor" : "business",
  "project" : "",
  "businessUnit" : "client",
  "organisation" : "",
  "trip" : "gfnh",
  "tripDescription" : "gnjyr",
  "location" : "domestic",
  "foreignExchange" : "",
  "applyFor" : "self",
  "other" : "",
  "travelId" : 466,
  "approvalStatus" : null
}, {
  "id" : null,
  "dateOfTravel" : "2024-05-04",
  "travelFor" : "business",
  "project" : "",
  "businessUnit" : "client",
  "organisation" : "",
  "trip" : "rfhwe",
  "tripDescription" : "eh",
  "location" : "domestic",
  "foreignExchange" : "",
  "applyFor" : "self",
  "other" : "",
  "travelId" : 676954,
  "approvalStatus" : null
}, {
  "id" : null,
  "dateOfTravel" : "2024-04-26",
  "travelFor" : "business",
  "project" : "",
  "businessUnit" : "client",
  "organisation" : "",
  "trip" : "klhy",
  "tripDescription" : "fyggh",
  "location" : "domestic",
  "foreignExchange" : "",
  "applyFor" : "self",
  "other" : "",
  "travelId" : 8698,
  "approvalStatus" : null
}, {
  "id" : null,
  "dateOfTravel" : "2024-04-27",
  "travelFor" : "business",
  "project" : "",
  "businessUnit" : "client",
  "organisation" : "",
  "trip" : "hyd",
  "tripDescription" : "dghugo",
  "location" : "domestic",
  "foreignExchange" : "",
  "applyFor" : "self",
  "other" : "",
  "travelId" : 43534,
  "approvalStatus" : null
}, {
  "id" : null,
  "dateOfTravel" : "2024-06-03",
  "travelFor" : "organisation",
  "project" : "",
  "businessUnit" : "",
  "organisation" : "organisation",
  "trip" : "delhi",
  "tripDescription" : "delhi trip",
  "location" : "domestic",
  "foreignExchange" : "",
  "applyFor" : "self",
  "other" : "",
  "travelId" : 3333,
  "approvalStatus" : null
}, {
  "id" : null,
  "dateOfTravel" : "2024-07-18",
  "travelFor" : "business",
  "project" : "",
  "businessUnit" : "client",
  "organisation" : "",
  "trip" : "abc",
  "tripDescription" : "anc trip",
  "location" : "domestic",
  "foreignExchange" : "",
  "applyFor" : "self",
  "other" : "",
  "travelId" : 3984,
  "approvalStatus" : null
}, {
  "id" : null,
  "dateOfTravel" : "2024-04-29",
  "travelFor" : "organisation",
  "project" : "",
  "businessUnit" : "",
  "organisation" : "organisation",
  "trip" : "patna",
  "tripDescription" : "holiday",
  "location" : "domestic",
  "foreignExchange" : "",
  "applyFor" : "self",
  "other" : "",
  "travelId" : 1557,
  "approvalStatus" : null
}, {
  "id" : null,
  "dateOfTravel" : "2024-04-28",
  "travelFor" : "business",
  "project" : "",
  "businessUnit" : "client",
  "organisation" : "",
  "trip" : "mp",
  "tripDescription" : "mp trip",
  "location" : "domestic",
  "foreignExchange" : "",
  "applyFor" : "self",
  "other" : "",
  "travelId" : 1986,
  "approvalStatus" : null
}, {
  "id" : null,
  "dateOfTravel" : "2024-05-04",
  "travelFor" : "business",
  "project" : "",
  "businessUnit" : "client",
  "organisation" : "",
  "trip" : "up",
  "tripDescription" : "up trip",
  "location" : "domestic",
  "foreignExchange" : "",
  "applyFor" : "self",
  "other" : "",
  "travelId" : 2003,
  "approvalStatus" : null
}, {
  "id" : null,
  "dateOfTravel" : "2024-05-05",
  "travelFor" : "business",
  "project" : "",
  "businessUnit" : "client",
  "organisation" : "",
  "trip" : "jfyjfi",
  "tripDescription" : "gfjyfiuv",
  "location" : "domestic",
  "foreignExchange" : "",
  "applyFor" : "self",
  "other" : "",
  "travelId" : 3725,
  "approvalStatus" : null
}, {
  "id" : null,
  "dateOfTravel" : "2024-05-23",
  "travelFor" : "business",
  "project" : "",
  "businessUnit" : "client",
  "organisation" : "",
  "trip" : "paris",
  "tripDescription" : "paris trip",
  "location" : "domestic",
  "foreignExchange" : "",
  "applyFor" : "self",
  "other" : "",
  "travelId" : 3392,
  "approvalStatus" : null
}, {
  "id" : null,
  "dateOfTravel" : "2024-05-10",
  "travelFor" : "business",
  "project" : "",
  "businessUnit" : "client",
  "organisation" : "",
  "trip" : "nbv",
  "tripDescription" : "nbv nbv",
  "location" : "domestic",
  "foreignExchange" : "",
  "applyFor" : "self",
  "other" : "",
  "travelId" : 8847,
  "approvalStatus" : null
}, {
  "id" : null,
  "dateOfTravel" : "2024-05-24",
  "travelFor" : "organisation",
  "project" : "",
  "businessUnit" : "",
  "organisation" : "organisation",
  "trip" : "poiu",
  "tripDescription" : "poiu",
  "location" : "domestic",
  "foreignExchange" : "",
  "applyFor" : "self",
  "other" : "",
  "travelId" : 1850,
  "approvalStatus" : null
}, {
  "id" : null,
  "dateOfTravel" : "2024-05-25",
  "travelFor" : "business",
  "project" : "",
  "businessUnit" : "client",
  "organisation" : "",
  "trip" : "uytr",
  "tripDescription" : "iuyt trip",
  "location" : "domestic",
  "foreignExchange" : "",
  "applyFor" : "self",
  "other" : "",
  "travelId" : 1016,
  "approvalStatus" : null
}, {
  "id" : null,
  "dateOfTravel" : "2024-05-12",
  "travelFor" : "business",
  "project" : "",
  "businessUnit" : "client",
  "organisation" : "",
  "trip" : "oiu",
  "tripDescription" : "poi",
  "location" : "domestic",
  "foreignExchange" : "",
  "applyFor" : "self",
  "other" : "",
  "travelId" : 9022,
  "approvalStatus" : null
} ]