[{"id":4,"dateOfTravel":"2024-03-21","travelFor":"project","project":"innovation","businessUnit":"","organisation":"","trip":"patna","tripDescription":"for client meeting","location":"domestic","foreignExchange":"","applyFor":"self","other":"","empId":5596,"triptravelDetails":[{"id":1,"type":"Travel","location":"","from":"patna","to":"heydrabad","checkIn":"","checkOut":"","departure":"2024-03-21"},{"id":2,"type":"Travel","location":"","from":"heydrabad","to":"patna","checkIn":"","checkOut":"","departure":"2024-03-21"}]},{"id":5,"dateOfTravel":"2024-03-21","travelFor":"project","project":"innovation","businessUnit":"","organisation":"","trip":"patna","tripDescription":"for client meeting","location":"domestic","foreignExchange":"","applyFor":"self","other":"","empId":5597,"triptravelDetails":[{"id":1,"type":"Travel","location":"","from":"patna","to":"heydrabad","checkIn":"","checkOut":"","departure":"2024-03-21"},{"id":2,"type":"Travel","location":"","from":"heydrabad","to":"patna","checkIn":"","checkOut":"","departure":"2024-03-21"}]},{"id":5,"dateOfTravel":"2024-03-21","travelFor":"project","project":"innovation","businessUnit":"","organisation":"","trip":"patna","tripDescription":"for client meeting","location":"domestic","foreignExchange":"","applyFor":"self","other":"","empId":5598,"triptravelDetails":[{"id":1,"type":"Travel","location":"","from":"patna","to":"heydrabad","checkIn":"","checkOut":"","departure":"2024-03-21"},{"id":2,"type":"Travel","location":"","from":"heydrabad","to":"patna","checkIn":"","checkOut":"","departure":"2024-03-21"}]},{"id":1,"dateOfTravel":null,"travelFor":null,"project":null,"businessUnit":null,"organisation":null,"trip":null,"tripDescription":null,"location":"","foreignExchange":null,"applyFor":null,"other":null,"empId":null,"triptravelDetails":null}]